chuk_tool_processor/__init__.py
chuk_tool_processor/config.py
chuk_tool_processor/py.typed
chuk_tool_processor/core/__init__.py
chuk_tool_processor/core/context.py
chuk_tool_processor/core/exceptions.py
chuk_tool_processor/core/processor.py
chuk_tool_processor/discovery/__init__.py
chuk_tool_processor/discovery/dynamic_provider.py
chuk_tool_processor/discovery/search.py
chuk_tool_processor/discovery/searchable.py
chuk_tool_processor/discovery/synonyms.py
chuk_tool_processor/execution/__init__.py
chuk_tool_processor/execution/bulkhead.py
chuk_tool_processor/execution/code_sandbox.py
chuk_tool_processor/execution/tool_executor.py
chuk_tool_processor/execution/strategies/__init__.py
chuk_tool_processor/execution/strategies/inprocess_strategy.py
chuk_tool_processor/execution/strategies/subprocess_strategy.py
chuk_tool_processor/execution/wrappers/__init__.py
chuk_tool_processor/execution/wrappers/caching.py
chuk_tool_processor/execution/wrappers/circuit_breaker.py
chuk_tool_processor/execution/wrappers/factory.py
chuk_tool_processor/execution/wrappers/observable.py
chuk_tool_processor/execution/wrappers/rate_limiting.py
chuk_tool_processor/execution/wrappers/redis_circuit_breaker.py
chuk_tool_processor/execution/wrappers/redis_rate_limiting.py
chuk_tool_processor/execution/wrappers/retry.py
chuk_tool_processor/guards/__init__.py
chuk_tool_processor/guards/assumption_trace.py
chuk_tool_processor/guards/base.py
chuk_tool_processor/guards/budget.py
chuk_tool_processor/guards/chain.py
chuk_tool_processor/guards/concurrency.py
chuk_tool_processor/guards/contract_guard.py
chuk_tool_processor/guards/models.py
chuk_tool_processor/guards/network_policy.py
chuk_tool_processor/guards/output_size.py
chuk_tool_processor/guards/per_tool.py
chuk_tool_processor/guards/plan_shape.py
chuk_tool_processor/guards/precondition.py
chuk_tool_processor/guards/provenance.py
chuk_tool_processor/guards/retry_safety.py
chuk_tool_processor/guards/runaway.py
chuk_tool_processor/guards/saturation.py
chuk_tool_processor-0.19.dist-info/METADATA
chuk_tool_processor-0.19.dist-info/WHEEL
chuk_tool_processor-0.19.dist-info/top_level.txt
chuk_tool_processor-0.19.dist-info/RECORD
