Metadata-Version: 2.4
Name: chuk-tool-processor
Version: 0.19
Summary: Async-native framework for registering, discovering, and executing tools referenced in LLM responses
Author-email: CHUK Team <chrishayuk@somejunkmailbox.com>
Maintainer-email: CHUK Team <chrishayuk@somejunkmailbox.com>
License: MIT
Keywords: llm,tools,async,ai,openai,mcp,model-context-protocol,tool-calling,function-calling
Classifier: Development Status :: 4 - Beta
Classifier: Intended Audience :: Developers
Classifier: License :: OSI Approved :: MIT License
Classifier: Operating System :: OS Independent
Classifier: Programming Language :: Python :: 3
Classifier: Programming Language :: Python :: 3.11
Classifier: Programming Language :: Python :: 3.12
Classifier: Programming Language :: Python :: 3.13
Classifier: Topic :: Software Development :: Libraries :: Python Modules
Classifier: Topic :: Scientific/Engineering :: Artificial Intelligence
Classifier: Framework :: AsyncIO
Classifier: Typing :: Typed
Requires-Python: >=3.11
Requires-Dist: chuk-mcp>=0.9
Requires-Dist: dotenv>=0.9.9
Requires-Dist: psutil>=7.0.0
Requires-Dist: pydantic>=2.11.3
Requires-Dist: uuid>=1.30
Provides-Extra: fast-json
Requires-Dist: orjson<4,>=3.10.0; extra == "fast-json"
Provides-Extra: redis
Requires-Dist: redis[hiredis]<6,>=5.0.0; extra == "redis"
Provides-Extra: full
Requires-Dist: orjson<4,>=3.10.0; extra == "full"
Provides-Extra: all
Requires-Dist: orjson<4,>=3.10.0; extra == "all"
Requires-Dist: redis[hiredis]<6,>=5.0.0; extra == "all"
